<?xml version="1.0" encoding="UTF-8" standalone="yes"?>
<contentHaul xmlns:a="http://www.appian.com/ae/types/2009">
    <versionUuid>_a-0000e394-8db7-8000-0bd6-01ef9001ef90_97176</versionUuid>
    <folder>
        <name>LMS Message Attachments</name>
        <uuid>203370fb-ce46-4b3e-8f8f-6e3a2a27e3e8_ATTACH</uuid>
        <description>Folder to hold attachments for Tempo messages made through the Library Management system application [Document Management] [Collaboration]</description>
        <parentUuid>995c0d08-12b9-4aa9-9c70-f7cac0d4d849_KC</parentUuid>
        <visibility>
            <advertise>false</advertise>
            <hierarchy>true</hierarchy>
            <indexable>true</indexable>
            <quota>false</quota>
            <searchable>true</searchable>
            <system>false</system>
            <unlogged>false</unlogged>
        </visibility>
    </folder>
    <roleMap public="true">
        <role inherit="true" allowForAll="false" name="readers">
            <users/>
            <groups/>
        </role>
        <role inherit="true" allowForAll="false" name="authors">
            <users/>
            <groups/>
        </role>
        <role inherit="true" allowForAll="false" name="administrators">
            <users/>
            <groups/>
        </role>
        <role inherit="false" allowForAll="false" name="denyReaders">
            <users/>
            <groups/>
        </role>
        <role inherit="false" allowForAll="false" name="denyAuthors">
            <users/>
            <groups/>
        </role>
        <role inherit="false" allowForAll="false" name="denyAdministrators">
            <users/>
            <groups/>
        </role>
    </roleMap>
    <history>
        <historyInfo versionUuid="_a-0000e394-8db7-8000-0bd6-01ef9001ef90_97176"/>
    </history>
</contentHaul>
